LICENSE
MANIFEST.in
README.md
setup.cfg
setup.py
podiant/__init__.py
podiant/connection.py
podiant/exceptions.py
podiant/nonces.py
podiant/settings.py
podiant/webhooks.py
podiant/api/__init__.py
podiant/api/client.py
podiant/api/proxy.py
podiant/api/transport.py
podiant_client.egg-info/PKG-INFO
podiant_client.egg-info/SOURCES.txt
podiant_client.egg-info/dependency_links.txt
podiant_client.egg-info/not-zip-safe
podiant_client.egg-info/requires.txt
podiant_client.egg-info/top_level.txt